ddn/__init__.py
ddn/dictdefaultnone.py
ddn-1.0.1.dist-info/LICENSE
ddn-1.0.1.dist-info/METADATA
ddn-1.0.1.dist-info/WHEEL
ddn-1.0.1.dist-info/top_level.txt
ddn-1.0.1.dist-info/RECORD
