Metadata-Version: 2.1
Name: ddn
Version: 1.0.1
Summary: DictDefaultNone. Get data from nested lists and dictionaries use simple syntax(eg.: dict1["k1"]["k2"][0]["k"]), if can‘t return None, no raise error
Home-page: https://github.com/DJMIN/ddn
Author: readerror
Author-email: readerror@sina.com
Maintainer: readerror
Maintainer-email: readerror@sina.com
License: GPL License
Platform: all
License-File: LICENSE
Requires-Dist: setuptools
Requires-Dist: wheel
Requires-Dist: twine
